multicaller/__init__.py
multicaller/multicaller.py
multicaller/abi/multiCall.json
multicallerbsc-0.0.0a13.dist-info/METADATA
multicallerbsc-0.0.0a13.dist-info/WHEEL
multicallerbsc-0.0.0a13.dist-info/top_level.txt
multicallerbsc-0.0.0a13.dist-info/RECORD
